hunter.pth
hunter/__init__.py
hunter/_event.c
hunter/_event.pxd
hunter/_event.pyx
hunter/_predicates.c
hunter/_predicates.pxd
hunter/_predicates.pyx
hunter/_tracer.c
hunter/_tracer.pxd
hunter/_tracer.pyx
hunter/_version.py
hunter/actions.py
hunter/config.py
hunter/const.py
hunter/event.py
hunter/predicates.py
hunter/remote.py
hunter/tracer.py
hunter/util.py
hunter/vendor/__init__.py
hunter/vendor/_compat.h
hunter/vendor/colorama/__init__.py
hunter/vendor/colorama/ansi.py
hunter/vendor/colorama/ansitowin32.py
hunter/vendor/colorama/initialise.py
hunter/vendor/colorama/win32.py
hunter/vendor/colorama/winterm.py
hunter-3.9.0.dist-info/licenses/LICENSE
hunter-3.9.0.dist-info/METADATA
hunter-3.9.0.dist-info/WHEEL
hunter-3.9.0.dist-info/entry_points.txt
hunter-3.9.0.dist-info/top_level.txt
hunter-3.9.0.dist-info/RECORD
