Metadata-Version: 2.4
Name: hunter
Version: 3.9.0
Summary: Hunter is a flexible code tracing toolkit.
Author-email: Ionel Cristian Mărieș <contact@ionelmc.ro>
License-Expression: BSD-2-Clause
Project-URL: Sources, https://github.com/ionelmc/python-hunter
Project-URL: Documentation, https://python-hunter.readthedocs.io/
Project-URL: Changelog, https://python-hunter.readthedocs.io/en/latest/changelog.html
Project-URL: Issue Tracker, https://github.com/ionelmc/python-hunter/issues
Keywords: trace,tracer,settrace,debugger,debugging,code,source
Classifier: Development Status :: 5 - Production/Stable
Classifier: Intended Audience :: Developers
Classifier: Operating System :: Unix
Classifier: Operating System :: POSIX
Classifier: Operating System :: Microsoft :: Windows
Classifier: Programming Language :: Python
Classifier: Programming Language :: Python :: 3
Classifier: Programming Language :: Python :: 3 :: Only
Classifier: Programming Language :: Python :: 3.9
Classifier: Programming Language :: Python :: 3.10
Classifier: Programming Language :: Python :: 3.11
Classifier: Programming Language :: Python :: 3.12
Classifier: Programming Language :: Python :: 3.13
Classifier: Programming Language :: Python :: Implementation :: CPython
Classifier: Programming Language :: Python :: Implementation :: PyPy
Classifier: Topic :: Utilities
Classifier: Topic :: Software Development :: Debuggers
Requires-Python: >=3.9
License-File: LICENSE
Requires-Dist: manhole>=1.5; platform_system != "Windows"
Dynamic: description
Dynamic: description-content-type
Dynamic: license-file
